dbsp_drp/__init__.py
dbsp_drp/adjust_splicing.py
dbsp_drp/coadding.py
dbsp_drp/fix_headers.py
dbsp_drp/fluxing.py
dbsp_drp/gui_helpers.py
dbsp_drp/manual_aperture.py
dbsp_drp/manual_splice.py
dbsp_drp/manual_tracing.py
dbsp_drp/p200_redux.py
dbsp_drp/qa.py
dbsp_drp/quicklook.py
dbsp_drp/reduction.py
dbsp_drp/show_spectrum.py
dbsp_drp/splicing.py
dbsp_drp/table_edit.py
dbsp_drp/telluric.py
dbsp_drp/trim.py
dbsp_drp/version.py
dbsp_drp/data/dbsp_qa.css
dbsp_drp/data/dbsp_qa.js
dbsp_drp/data/sens_blue_1200_5000_d55.fits
dbsp_drp/data/sens_blue_300_3990_d55.fits
dbsp_drp/data/sens_blue_600_4000_d55.fits
dbsp_drp/data/sens_blue_600_4000_d68.fits
dbsp_drp/data/sens_red_1200_7100_d68.fits
dbsp_drp/data/sens_red_1200_9400_d55.fits
dbsp_drp/data/sens_red_316_7500_d55.fits
dbsp_drp/data/sens_red_600_10000_d55.fits
dbsp_drp/tests/__init__.py
dbsp_drp/tests/conftest.py
dbsp_drp/tests/test_coadding.py
dbsp_drp/tests/test_fluxing.py
dbsp_drp/tests/test_quicklook.py
dbsp_drp/tests/test_splicing.py
dbsp_drp/tests/test_table_edit.py
dbsp_drp/tests/files/ql_test_data/blue0022.fits
dbsp_drp/tests/files/ql_test_data/blue0031.fits
dbsp_drp/tests/files/ql_test_data/blue0050.fits
dbsp_drp/tests/files/ql_test_data/red0022.fits
dbsp_drp/tests/files/ql_test_data/red0033.fits
dbsp_drp/tests/files/ql_test_data/red0052.fits
dbsp_drp/tests/files/table_edit_test_data/red0001_bias_no_radec.fits
dbsp_drp/tests/files/table_edit_test_data/red0003_arc_no_radec.fits
dbsp_drp/tests/files/table_edit_test_data/red0005_flat_no_radec.fits
dbsp_drp/tests/files/table_edit_test_data/red0006_flat_yes_radec.fits
dbsp_drp/tests/files/table_edit_test_data/red0007_science.fits
DBSP_DRP-1.0.0.post4.dist-info/LICENSE
DBSP_DRP-1.0.0.post4.dist-info/METADATA
DBSP_DRP-1.0.0.post4.dist-info/WHEEL
DBSP_DRP-1.0.0.post4.dist-info/entry_points.txt
DBSP_DRP-1.0.0.post4.dist-info/top_level.txt
DBSP_DRP-1.0.0.post4.dist-info/RECORD
