Metadata-Version: 2.1
Name: DBSP-DRP
Version: 1.0.0.post4
Summary: "Automated Data Reduction Pipeline for Palomar's Double Spectrograph"
Home-page: https://github.com/finagle29/DBSP_DRP
Author: Milan Sharma Mandigo-Stoba
Author-email: finagle29@gmail.com
License: BSD-3
Requires-Python: >=3.7
License-File: LICENSE
Requires-Dist: numpy
Requires-Dist: astropy
Requires-Dist: scipy
Requires-Dist: matplotlib
Requires-Dist: configobj
Requires-Dist: packaging
Requires-Dist: pytest
Requires-Dist: yattag
Requires-Dist: pypeit
Requires-Dist: tqdm
